{"name":"Rastislav Kuspal","hand":"L","TOHL12pre":{"number":"77","pos":"C","cd":"OK","ij":"","it":"78","sp":"61","st":"53","en":"83","du":"58","di":"90","sk":"49","pa":"44","pc":"63","df":"77","sc":"74","ex":"72","ld":"57","ov":"68"},"TOHL11":{"number":"77","pos":"C","cd":"OK","ij":"","it":"78","sp":"61","st":"53","en":"83","du":"58","di":"90","sk":"49","pa":"44","pc":"63","df":"77","sc":"74","ex":"68","ld":"57","ov":"68","rookie":false,"age":"29","height":185,"weight":85,"salary":"99000","contract":"2"}}