{"name":"Wim Pimpelmans","hand":"L","TOHL12pre":{"number":"10","pos":"RW","cd":"OK","ij":"","it":"43","sp":"84","st":"62","en":"79","du":"58","di":"62","sk":"80","pa":"60","pc":"65","df":"53","sc":"58","ex":"43","ld":"62","ov":"67","height":180,"weight":80,"rookie":false,"salary":"80000","age":"19","contract":"3"},"TOHL11":{"number":"10","pos":"RW","cd":"OK","ij":"","it":"43","sp":"84","st":"62","en":"79","du":"58","di":"62","sk":"80","pa":"60","pc":"65","df":"53","sc":"58","ex":"39","ld":"62","ov":"67","height":180,"weight":80,"rookie":true,"salary":"80000","age":"18","contract":"4"}}