{"name":"Stefan Rupf","hand":"L","TOHL12pre":{"number":"21","pos":"D","cd":"OK","ij":"","it":"71","sp":"66","st":"78","en":"69","du":"77","di":"46","sk":"42","pa":"56","pc":"57","df":"73","sc":"62","ex":"64","ld":"40","ov":"69","height":188,"weight":100,"rookie":false,"salary":"25000"},"TOHL11":{"number":"21","pos":"D","cd":"OK","ij":"","it":"71","sp":"66","st":"78","en":"69","du":"77","di":"46","sk":"42","pa":"56","pc":"57","df":"73","sc":"62","ex":"60","ld":"40","ov":"69","rookie":false,"age":"32","height":188,"weight":100,"salary":"25000","contract":"3"}}