{"name":"Bernd Beinsteller","hand":"L","TOHL12pre":{"number":"46","pos":"D","cd":"OK","ij":"","it":"71","sp":"76","st":"62","en":"63","du":"63","di":"73","sk":"74","pa":"66","pc":"68","df":"80","sc":"61","ex":"58","ld":"45","ov":"74","height":188,"weight":88,"rookie":false,"salary":"170000"},"TOHL11":{"number":"46","pos":"D","cd":"OK","ij":"","it":"71","sp":"76","st":"62","en":"63","du":"63","di":"73","sk":"74","pa":"66","pc":"68","df":"80","sc":"61","ex":"54","ld":"45","ov":"74","rookie":false,"age":"32","height":188,"weight":88,"salary":"170000","contract":"2"}}