{"name":"Gisbert Ndesu","hand":"L","TOHL12pre":{"number":"53","pos":"D","cd":"OK","ij":"","it":"85","sp":"55","st":"94","en":"50","du":"58","di":"48","sk":"64","pa":"37","pc":"55","df":"75","sc":"47","ex":"72","ld":"65","ov":"71"},"TOHL11":{"number":"48","pos":"D","cd":"OK","ij":"","it":"85","sp":"55","st":"94","en":"50","du":"58","di":"48","sk":"64","pa":"37","pc":"55","df":"75","sc":"47","ex":"67","ld":"65","ov":"71","rookie":"","age":"32","height":"6 ft 4","weight":"244","salary":"50.000","contract":"3"}}