{"name":"Anders Allsgewollt","hand":"L","TOHL12pre":{"number":"32","pos":"RW","cd":"OK","ij":"","it":"82","sp":"56","st":"85","en":"78","du":"77","di":"60","sk":"72","pa":"61","pc":"61","df":"71","sc":"53","ex":"74","ld":"42","ov":"71"},"TOHL11":{"number":"32","pos":"RW","cd":"OK","ij":"","it":"82","sp":"56","st":"85","en":"78","du":"77","di":"60","sk":"72","pa":"61","pc":"61","df":"71","sc":"53","ex":"71","ld":"42","ov":"70","rookie":"","age":"31","height":"6 ft 4","weight":"216","salary":"35.000","contract":"3"}}