{"name":"Gosey Bumps","hand":"L","TOHL11":{"number":"38","pos":"LW","cd":"OK","ij":"","it":"70","sp":"82","st":"59","en":"71","du":"98","di":"81","sk":"79","pa":"56","pc":"63","df":"70","sc":"66","ex":"89","ld":"82","ov":"72","rookie":false,"age":"29","height":170,"weight":86,"salary":"200000","contract":"1"},"TOHL12pre":{"number":"39","pos":"LW","cd":"OK","ij":"","it":"70","sp":"82","st":"59","en":"71","du":"98","di":"81","sk":"79","pa":"56","pc":"63","df":"70","sc":"66","ex":"93","ld":"82","ov":"73"}}