{"name":"Colin Terric","hand":"R","TOHL12pre":{"number":"63","pos":"RW","cd":"OK","ij":"","it":"68","sp":"62","st":"71","en":"70","du":"65","di":"30","sk":"72","pa":"62","pc":"66","df":"60","sc":"64","ex":"58","ld":"36","ov":"69"},"TOHL11":{"number":"63","pos":"RW","cd":"OK","ij":"","it":"68","sp":"62","st":"71","en":"70","du":"65","di":"30","sk":"72","pa":"62","pc":"66","df":"60","sc":"64","ex":"55","ld":"36","ov":"69","rookie":"","age":"33","height":"6 ft 3","weight":"210","salary":"25.000","contract":"3"}}