{"name":"Elviz Suezer","hand":"L","TOHL12pre":{"number":"71","pos":"RW","cd":"OK","ij":"","it":"45","sp":"76","st":"64","en":"71","du":"52","di":"48","sk":"76","pa":"89","pc":"89","df":"67","sc":"80","ex":"64","ld":"83","ov":"79","height":178,"weight":83,"rookie":false,"salary":"100000","age":"33","contract":"2"},"TOHL11":{"number":"71","pos":"RW","cd":"OK","ij":"","it":"45","sp":"76","st":"64","en":"71","du":"52","di":"48","sk":"76","pa":"89","pc":"89","df":"67","sc":"80","ex":"60","ld":"83","ov":"79","rookie":false,"age":"32","height":178,"weight":83,"salary":"100000","contract":"3"}}