{"name":"Bodo Grimmig","hand":"R","TOHL12pre":{"number":"15","pos":"LW","cd":"OK","ij":"","it":"74","sp":"69","st":"49","en":"71","du":"83","di":"56","sk":"70","pa":"60","pc":"79","df":"69","sc":"70","ex":"65","ld":"36","ov":"72","height":178,"weight":81,"rookie":false,"salary":"25000","age":"34","contract":"2"},"TOHL11":{"number":"15","pos":"LW","cd":"OK","ij":"","it":"74","sp":"69","st":"49","en":"71","du":"83","di":"56","sk":"70","pa":"60","pc":"79","df":"69","sc":"70","ex":"60","ld":"36","ov":"71","rookie":false,"age":"33","height":178,"weight":81,"salary":"25000","contract":"3"}}