{"name":"Fredrik Hulverson","hand":"R","TOHL12pre":{"number":"14","pos":"C","cd":"OK","ij":"","it":"79","sp":"71","st":"74","en":"80","du":"72","di":"84","sk":"75","pa":"78","pc":"77","df":"81","sc":"71","ex":"99","ld":"48","ov":"80"},"TOHL11":{"number":"14","pos":"C","cd":"OK","ij":"","it":"79","sp":"71","st":"74","en":"80","du":"72","di":"84","sk":"75","pa":"78","pc":"77","df":"81","sc":"71","ex":"96","ld":"48","ov":"80","rookie":false,"age":"35","height":191,"weight":95,"salary":"215000","contract":"2"}}